Metadata-Version: 2.4
Name: data-explorer-in
Version: 0.1.0
Summary: Exploration des données économiques via l'API World Bank
Author-email: Ibrahima Ndao <ndaoibrahima037@gmail.com>
License-Expression: MIT
Requires-Python: >=3.7
Requires-Dist: pandas
Requires-Dist: requests
